immoscrapy/__init__.py
immoscrapy/cli.py
immoscrapy/immoscrapy.py
immoscrapy/version.py
immoscrapy-1.0.1.dist-info/LICENSE
immoscrapy-1.0.1.dist-info/METADATA
immoscrapy-1.0.1.dist-info/WHEEL
immoscrapy-1.0.1.dist-info/entry_points.txt
immoscrapy-1.0.1.dist-info/top_level.txt
immoscrapy-1.0.1.dist-info/RECORD
